bookmanager/__init__.py
bookmanager/__version__.py
bookmanager/book.py
bookmanager/command.py
bookmanager/config.py
bookmanager/cover.py
bookmanager/document.py
bookmanager/git.py
bookmanager/run.py
bookmanager/util.py
bookmanager/template/disclaimer-references.md
bookmanager/template/disclaimer-short.md
bookmanager/template/disclaimer.md
bookmanager/template/empty.md
bookmanager/template/epub/epub-dejavu.css
bookmanager/template/epub/epub-indent.css
bookmanager/template/epub/epub-ok.css
bookmanager/template/epub/epub-opensans.css
bookmanager/template/epub/epub.css
bookmanager/template/epub/ieee-with-url.csl
bookmanager/template/epub/metadata.txt
bookmanager/template/epub/cover/cover-image.png
bookmanager/template/epub/fonts/DejaVuSerif-Bold.ttf
bookmanager/template/epub/fonts/DejaVuSerif-BoldItalic.ttf
bookmanager/template/epub/fonts/DejaVuSerif-Italic.ttf
bookmanager/template/epub/fonts/DejaVuSerif.ttf
bookmanager/template/epub/fonts/DejaVuSerifCondensed-Bold.ttf
bookmanager/template/epub/fonts/DejaVuSerifCondensed-BoldItalic.ttf
bookmanager/template/epub/fonts/DejaVuSerifCondensed-Italic.ttf
bookmanager/template/epub/fonts/DejaVuSerifCondensed.ttf
bookmanager/template/epub/fonts/OpenSans-Bold.ttf
bookmanager/template/epub/fonts/OpenSans-BoldItalic.ttf
bookmanager/template/epub/fonts/OpenSans-Emoji.ttf
bookmanager/template/epub/fonts/OpenSans-ExtraBold.ttf
bookmanager/template/epub/fonts/OpenSans-ExtraBoldItalic.ttf
bookmanager/template/epub/fonts/OpenSans-Italic.ttf
bookmanager/template/epub/fonts/OpenSans-Light.ttf
bookmanager/template/epub/fonts/OpenSans-LightItalic.ttf
bookmanager/template/epub/fonts/OpenSans-Regular.ttf
bookmanager/template/epub/fonts/OpenSans-Semibold.ttf
bookmanager/template/epub/fonts/OpenSans-SemiboldItalic.ttf
bookmanager/template/epub/fonts/OpenSansEmoji.ttf
bookmanager/template/epub/fonts/Oswald-Bold.ttf
bookmanager/template/epub/fonts/Oswald-Light.ttf
bookmanager/template/epub/fonts/Oswald-Regular.ttf
cyberaide_bookmanager-0.2.44.dist-info/LICENSE
cyberaide_bookmanager-0.2.44.dist-info/METADATA
cyberaide_bookmanager-0.2.44.dist-info/WHEEL
cyberaide_bookmanager-0.2.44.dist-info/entry_points.txt
cyberaide_bookmanager-0.2.44.dist-info/top_level.txt
cyberaide_bookmanager-0.2.44.dist-info/RECORD
