Metadata-Version: 2.1
Name: cyberaide-bookmanager
Version: 0.2.44
Summary: Creating Books from content in different git and other cloud services.
Home-page: https://github.com/cyberaide/bookmanager
Author: Gregor von Laszewski
Author-email: laszewski@gmail.com
License: Apache 2.0
Keywords: pandoc book proceedings markdown epub
Classifier: Development Status :: 5 - Production/Stable
Classifier: Environment :: Console
Classifier: Environment :: MacOS X
Classifier: Environment :: OpenStack
Classifier: Environment :: Other Environment
Classifier: Environment :: Plugins
Classifier: Intended Audience :: Information Technology
Classifier: Intended Audience :: Developers
Classifier: Intended Audience :: Education
Classifier: Intended Audience :: Science/Research
Classifier: Intended Audience :: System Administrators
Classifier: License :: OSI Approved :: Apache Software License
Classifier: Natural Language :: English
Classifier: Operating System :: OS Independent
Classifier: Operating System :: MacOS
Classifier: Operating System :: Microsoft :: Windows :: Windows 10
Classifier: Operating System :: Unix
Classifier: Programming Language :: Python
Classifier: Programming Language :: Python :: 3.9
Classifier: Programming Language :: Python :: 3.10
Classifier: Topic :: Internet
Classifier: Topic :: Scientific/Engineering
Classifier: Topic :: Software Development :: Libraries
Classifier: Topic :: Software Development :: User Interfaces
Classifier: Topic :: System
Classifier: Topic :: System :: Distributed Computing
Classifier: Topic :: System :: Shells
Classifier: Topic :: Utilities
License-File: LICENSE
Requires-Dist: oyaml
Requires-Dist: docopt
Requires-Dist: requests
Requires-Dist: colorama
Requires-Dist: tabulate
Requires-Dist: munch
Requires-Dist: pillow
Requires-Dist: markdown (==3.0)
Requires-Dist: cloudmesh-common
Requires-Dist: cloudmesh-git
Requires-Dist: ebooklib
